bletracking/__init__.py
bletracking/bletracking.py
bletracking/check_area_entering.py
bletracking/db_init.py
bletracking/db_update.py
bletracking/generate_mocked_data.py
bletracking/publish_to_socket.py
helpers/BGColor.py
helpers/SQLite.py
helpers/__init__.py
bletracking-0.1.0.dist-info/METADATA
bletracking-0.1.0.dist-info/WHEEL
bletracking-0.1.0.dist-info/top_level.txt
bletracking-0.1.0.dist-info/RECORD
