Metadata-Version: 2.1
Name: bletracking
Version: 0.1.0
Summary: bletracking
Home-page: UNKNOWN
Author: jaytrairat
Author-email: <jay.trairat@gmail.com>
License: UNKNOWN
Keywords: jaytrairat
Platform: UNKNOWN
Classifier: Programming Language :: Python :: 3
